c2cgeoportal_commons/__init__.py
c2cgeoportal_commons/py.typed
c2cgeoportal_commons/alembic/env.py
c2cgeoportal_commons/alembic/main/028477929d13_add_technical_roles.py
c2cgeoportal_commons/alembic/main/04f05bfbb05e_remove_the_old_is_expanded_column.py
c2cgeoportal_commons/alembic/main/116b9b79fc4d_internal_and_external_layer_tables_.py
c2cgeoportal_commons/alembic/main/1418cb05921b_merge_1_6_and_master_branches.py
c2cgeoportal_commons/alembic/main/164ac0819a61_add_image_format_to_wmts_layer.py
c2cgeoportal_commons/alembic/main/166ff2dcc48d_create_database.py
c2cgeoportal_commons/alembic/main/16e43f8c0330_remove_old_metadata_column.py
c2cgeoportal_commons/alembic/main/1d5d4abfebd1_add_restricted_theme.py
c2cgeoportal_commons/alembic/main/1de20166b274_remove_v1_artifacts.py
c2cgeoportal_commons/alembic/main/20137477bd02_update_icons_url.py
c2cgeoportal_commons/alembic/main/21f11066f8ec_trigger_on_role_updates_user_in_static.py
c2cgeoportal_commons/alembic/main/22e6dfb556de_add_description_tree_.py
c2cgeoportal_commons/alembic/main/29f2a32859ec_merge_1_6_and_master_branches.py
c2cgeoportal_commons/alembic/main/2b8ed8c1df94_set_layergroup_treeitem_is_as_a_primary_.py
c2cgeoportal_commons/alembic/main/2e57710fecfe_update_the_ogc_server_for_ogc_api.py
c2cgeoportal_commons/alembic/main/32527659d57b_move_exclude_properties_from_layerv1_to_.py
c2cgeoportal_commons/alembic/main/32b21aa1d0ed_merge_e004f76e951a_and_e004f76e951a_.py
c2cgeoportal_commons/alembic/main/338b57593823_remove_trigger_on_role_name_change.py
c2cgeoportal_commons/alembic/main/415746eb9f6_changes_for_v2.py
c2cgeoportal_commons/alembic/main/44c91d82d419_add_table_log.py
c2cgeoportal_commons/alembic/main/5109242131ce_add_column_time_widget.py
c2cgeoportal_commons/alembic/main/52916d8fde8b_add_sql_fields_to_vector_tiles.py
c2cgeoportal_commons/alembic/main/53ba1a68d5fe_add_theme_to_fulltextsearch.py
c2cgeoportal_commons/alembic/main/54645a535ad6_add_ordering_in_relation.py
c2cgeoportal_commons-2.9.0.388.dist-info/METADATA
c2cgeoportal_commons-2.9.0.388.dist-info/WHEEL
c2cgeoportal_commons-2.9.0.388.dist-info/top_level.txt
c2cgeoportal_commons-2.9.0.388.dist-info/RECORD
